mrkdwn_analysis/__init__.py
mrkdwn_analysis/markdown_analyzer.py
test/__init__.py
markdown_analysis-0.1.4.dist-info/LICENSE
markdown_analysis-0.1.4.dist-info/METADATA
markdown_analysis-0.1.4.dist-info/WHEEL
markdown_analysis-0.1.4.dist-info/top_level.txt
markdown_analysis-0.1.4.dist-info/RECORD
