Metadata-Version: 2.2
Name: markdown_analysis
Version: 0.1.4
Home-page: https://github.com/yannbanas/mrkdwn_analysis
Author: yannbanas
Author-email: yannbanas@gmail.com
Classifier: Development Status :: 2 - Pre-Alpha
Classifier: Intended Audience :: Developers
Classifier: License :: OSI Approved :: MIT License
Classifier: Programming Language :: Python :: 3.11
License-File: LICENSE
Requires-Dist: urllib3
Requires-Dist: requests
Requires-Dist: beautifulsoup4
Requires-Dist: markdownify
Dynamic: author
Dynamic: author-email
Dynamic: classifier
Dynamic: description
Dynamic: description-content-type
Dynamic: home-page
Dynamic: requires-dist
